ipmg/__init__.py
ipmg/discover.py
ipmg/io_handlers.py
ipmg/main.py
ipmg/ping.py
ipmg/reporting.py
ipmg/security.py
ipmg/utils.py
ipmg-1.0.2.dist-info/licenses/LICENSE
ipmg-1.0.2.dist-info/METADATA
ipmg-1.0.2.dist-info/WHEEL
ipmg-1.0.2.dist-info/entry_points.txt
ipmg-1.0.2.dist-info/top_level.txt
ipmg-1.0.2.dist-info/RECORD
