Metadata-Version: 2.4
Name: ipmg
Version: 1.0.2
Summary: IP Management & Ping Monitoring CLI Tool
Author: Sameer Alam
License: MIT
Requires-Python: >=3.8
License-File: LICENSE
Requires-Dist: pandas
Requires-Dist: tqdm
Requires-Dist: openpyxl
Requires-Dist: rich
Provides-Extra: dev
Requires-Dist: pytest; extra == "dev"
Requires-Dist: black; extra == "dev"
Requires-Dist: ruff; extra == "dev"
Dynamic: license-file
